{
  "date": "2026-04-28",
  "fetched_at": "2026-04-28T20:32:44.142111Z",
  "stocks": {
    "NOVO-B.CO": {
      "name": "Novo Nordisk B",
      "price": 265.15,
      "prev_close": 263.5,
      "pct_change": 0.63,
      "source": "yfinance"
    },
    "MAERSK-B.CO": {
      "name": "Maersk B",
      "price": 14990.0,
      "prev_close": 14755.0,
      "pct_change": 1.59,
      "source": "yfinance"
    },
    "DSV.CO": {
      "name": "DSV",
      "price": 1665.5,
      "prev_close": 1659.0,
      "pct_change": 0.39,
      "source": "yfinance"
    }
  }
}