{
  "date": "2026-06-25",
  "fetched_at": "2026-06-25T09:45:04.358957+00:00",
  "stocks": {
    "NOVO-B.CO": {
      "price": 316.0,
      "pct_1d": 1.43,
      "pct_5d": 12.82,
      "pct_20d": 8.93,
      "pe_forward": 14.643833,
      "pe_trailing": 11.524435,
      "div_yield": 5.1,
      "volume_ratio": 0.21,
      "52w_high": 464.6,
      "52w_low": 224.25,
      "pct_from_52w_high": -31.98,
      "pct_from_52w_low": 40.91,
      "revenue_growth": 0.24,
      "earnings_growth": 0.671,
      "market_cap": 1398886367232,
      "sector": "Healthcare",
      "industry": "Drug Manufacturers - General",
      "next_earnings_date": "2026-08-05",
      "technical": {
        "method": "yfinance_historical",
        "rsi": 68.5,
        "rsi_proxy": 68.5,
        "macd_line": 7.5505,
        "bb_upper": 312.9816,
        "bb_mid": 287.945,
        "bb_lower": 262.9084,
        "bb_position": 106.0,
        "atr": 9.9464,
        "stoch": 99.3,
        "stoch_proxy": 99.3,
        "sma50": 279.27,
        "sma200": 301.92,
        "sma50_vs_price": 13.15,
        "sma200_vs_price": 4.66,
        "volume_ratio": 0.21,
        "momentum_5d": 12.82,
        "momentum_20d": 8.93,
        "momentum_divergence": 3.89,
        "pct_from_52w_high": -31.98,
        "pct_from_52w_low": 40.91
      }
    },
    "MAERSK-B.CO": {
      "price": 16190.0,
      "pct_1d": 0.81,
      "pct_5d": 5.13,
      "pct_20d": 5.54,
      "pe_forward": -39.30242,
      "pe_trailing": 22.807636,
      "div_yield": 2.99,
      "volume_ratio": 0.04,
      "52w_high": 18865.0,
      "52w_low": 11620.0,
      "pct_from_52w_high": -14.18,
      "pct_from_52w_low": 39.33,
      "revenue_growth": -0.026,
      "earnings_growth": -0.946,
      "market_cap": 234510483456,
      "sector": "Industrials",
      "industry": "Marine Shipping",
      "next_earnings_date": "2026-08-06",
      "technical": {
        "method": "yfinance_historical",
        "rsi": 35.6,
        "rsi_proxy": 35.6,
        "macd_line": 66.0742,
        "bb_upper": 18417.4461,
        "bb_mid": 16559.25,
        "bb_lower": 14701.0539,
        "bb_position": 40.1,
        "atr": 720.7143,
        "stoch": 31.7,
        "stoch_proxy": 31.7,
        "sma50": 15649.2,
        "sma200": 14426.33,
        "sma50_vs_price": 3.46,
        "sma200_vs_price": 12.23,
        "volume_ratio": 0.03,
        "momentum_5d": 5.13,
        "momentum_20d": 5.54,
        "momentum_divergence": -0.41,
        "pct_from_52w_high": -14.18,
        "pct_from_52w_low": 39.33
      }
    },
    "MAERSK-A.CO": {
      "price": 15740.0,
      "pct_1d": 0.9,
      "pct_5d": 4.58,
      "pct_20d": 4.79,
      "pe_forward": null,
      "pe_trailing": 22.17526,
      "div_yield": 3.08,
      "volume_ratio": 0.06,
      "52w_high": 18320.0,
      "52w_low": 11520.0,
      "pct_from_52w_high": -14.08,
      "pct_from_52w_low": 36.63,
      "revenue_growth": -0.026,
      "earnings_growth": -0.946,
      "market_cap": 227992272896,
      "sector": "Industrials",
      "industry": "Marine Shipping",
      "next_earnings_date": "2026-08-06",
      "technical": {
        "method": "yfinance_historical",
        "rsi": 34.3,
        "rsi_proxy": 34.3,
        "macd_line": 27.8957,
        "bb_upper": 17873.376,
        "bb_mid": 16130.0,
        "bb_lower": 14386.624,
        "bb_position": 38.8,
        "atr": 622.1429,
        "stoch": 30.1,
        "stoch_proxy": 30.1,
        "sma50": 15371.8,
        "sma200": 14295.26,
        "sma50_vs_price": 2.4,
        "sma200_vs_price": 10.11,
        "volume_ratio": 0.04,
        "momentum_5d": 4.58,
        "momentum_20d": 4.79,
        "momentum_divergence": -0.21,
        "pct_from_52w_high": -14.08,
        "pct_from_52w_low": 36.63
      }
    },
    "DSV.CO": {
      "price": 1572.0,
      "pct_1d": 1.39,
      "pct_5d": 3.08,
      "pct_20d": 0.32,
      "pe_forward": 18.137474,
      "pe_trailing": 51.727543,
      "div_yield": 0.45,
      "volume_ratio": 0.14,
      "52w_high": 1913.5,
      "52w_low": 1233.0,
      "pct_from_52w_high": -17.85,
      "pct_from_52w_low": 27.49,
      "revenue_growth": 0.689,
      "earnings_growth": -0.429,
      "market_cap": 375024910336,
      "sector": "Industrials",
      "industry": "Integrated Freight & Logistics",
      "next_earnings_date": "2026-07-22",
      "technical": {
        "method": "yfinance_historical",
        "rsi": 43.1,
        "rsi_proxy": 43.1,
        "macd_line": -7.4102,
        "bb_upper": 1632.9777,
        "bb_mid": 1573.075,
        "bb_lower": 1513.1723,
        "bb_position": 49.1,
        "atr": 46.3571,
        "stoch": 49.5,
        "stoch_proxy": 49.5,
        "sma50": 1584.72,
        "sma200": 1536.71,
        "sma50_vs_price": -0.8,
        "sma200_vs_price": 2.3,
        "volume_ratio": 0.14,
        "momentum_5d": 3.08,
        "momentum_20d": 0.32,
        "momentum_divergence": 2.76,
        "pct_from_52w_high": -17.85,
        "pct_from_52w_low": 27.49
      }
    },
    "ORSTED.CO": {
      "price": 149.85,
      "pct_1d": 1.73,
      "pct_5d": 3.17,
      "pct_20d": -8.77,
      "pe_forward": 15.539689,
      "pe_trailing": null,
      "div_yield": null,
      "volume_ratio": 0.15,
      "52w_high": 327.5,
      "52w_low": 102.82325,
      "pct_from_52w_high": -54.24,
      "pct_from_52w_low": 45.74,
      "revenue_growth": 0.334,
      "earnings_growth": -0.849,
      "market_cap": 197961154560,
      "sector": "Utilities",
      "industry": "Utilities - Renewable",
      "next_earnings_date": "2026-05-06",
      "technical": {
        "method": "yfinance_historical",
        "rsi": 34.6,
        "rsi_proxy": 34.6,
        "macd_line": -3.9151,
        "bb_upper": 169.7091,
        "bb_mid": 156.09,
        "bb_lower": 142.4709,
        "bb_position": 27.1,
        "atr": 4.625,
        "stoch": 32.9,
        "stoch_proxy": 32.9,
        "sma50": 161.06,
        "sma200": 141.14,
        "sma50_vs_price": -6.96,
        "sma200_vs_price": 6.17,
        "volume_ratio": 0.15,
        "momentum_5d": 3.17,
        "momentum_20d": -8.77,
        "momentum_divergence": 11.94,
        "pct_from_52w_high": -54.24,
        "pct_from_52w_low": 45.74
      }
    },
    "CARL-B.CO": {
      "price": 885.6,
      "pct_1d": 1.03,
      "pct_5d": 6.29,
      "pct_20d": -0.56,
      "pe_forward": 12.537865,
      "pe_trailing": 19.73262,
      "div_yield": 3.31,
      "volume_ratio": 0.2,
      "52w_high": 1015.0,
      "52w_low": 737.4,
      "pct_from_52w_high": -12.75,
      "pct_from_52w_low": 20.1,
      "revenue_growth": null,
      "earnings_growth": null,
      "market_cap": 117051580416,
      "sector": "Consumer Defensive",
      "industry": "Beverages - Brewers",
      "next_earnings_date": null,
      "technical": {
        "method": "yfinance_historical",
        "rsi": 79.2,
        "rsi_proxy": 79.2,
        "macd_line": 4.847,
        "bb_upper": 882.6444,
        "bb_mid": 847.92,
        "bb_lower": 813.1956,
        "bb_position": 104.3,
        "atr": 17.7286,
        "stoch": 96.8,
        "stoch_proxy": 96.8,
        "sma50": 845.39,
        "sma200": 815.26,
        "sma50_vs_price": 4.76,
        "sma200_vs_price": 8.63,
        "volume_ratio": 0.2,
        "momentum_5d": 6.29,
        "momentum_20d": -0.56,
        "momentum_divergence": 6.85,
        "pct_from_52w_high": -12.75,
        "pct_from_52w_low": 20.1
      }
    },
    "PNDORA.CO": {
      "price": 703.2,
      "pct_1d": 2.12,
      "pct_5d": 7.92,
      "pct_20d": 19.03,
      "pe_forward": 18.128338,
      "pe_trailing": 10.571258,
      "div_yield": 3.19,
      "volume_ratio": 0.32,
      "52w_high": 1126.0,
      "52w_low": 430.0,
      "pct_from_52w_high": -37.55,
      "pct_from_52w_low": 63.53,
      "revenue_growth": -0.032,
      "earnings_growth": -0.1,
      "market_cap": 52599803904,
      "sector": "Consumer Cyclical",
      "industry": "Luxury Goods",
      "next_earnings_date": "2026-05-06",
      "technical": {
        "method": "yfinance_historical",
        "rsi": 84.8,
        "rsi_proxy": 84.8,
        "macd_line": 34.1493,
        "bb_upper": 695.4509,
        "bb_mid": 627.1,
        "bb_lower": 558.7491,
        "bb_position": 105.7,
        "atr": 23.1286,
        "stoch": 100.0,
        "stoch_proxy": 100.0,
        "sma50": 562.19,
        "sma200": 624.0,
        "sma50_vs_price": 25.08,
        "sma200_vs_price": 12.69,
        "volume_ratio": 0.37,
        "momentum_5d": 7.92,
        "momentum_20d": 19.03,
        "momentum_divergence": -11.11,
        "pct_from_52w_high": -37.55,
        "pct_from_52w_low": 63.53
      }
    },
    "TRYG.CO": {
      "price": 149.2,
      "pct_1d": -0.53,
      "pct_5d": -0.8,
      "pct_20d": -2.36,
      "pe_forward": 14.510626,
      "pe_trailing": 17.450293,
      "div_yield": 5.73,
      "volume_ratio": 0.12,
      "52w_high": 170.6,
      "52w_low": 146.5,
      "pct_from_52w_high": -12.54,
      "pct_from_52w_low": 1.84,
      "revenue_growth": 0.022,
      "earnings_growth": -0.139,
      "market_cap": 88907956224,
      "sector": "Financial Services",
      "industry": "Insurance - Diversified",
      "next_earnings_date": "2026-07-10",
      "technical": {
        "method": "yfinance_historical",
        "rsi": 55.3,
        "rsi_proxy": 55.3,
        "macd_line": -0.449,
        "bb_upper": 152.602,
        "bb_mid": 149.935,
        "bb_lower": 147.268,
        "bb_position": 36.2,
        "atr": 2.0071,
        "stoch": 43.5,
        "stoch_proxy": 43.5,
        "sma50": 152.14,
        "sma200": 154.48,
        "sma50_vs_price": -1.93,
        "sma200_vs_price": -3.42,
        "volume_ratio": 0.13,
        "momentum_5d": -0.8,
        "momentum_20d": -2.36,
        "momentum_divergence": 1.56,
        "pct_from_52w_high": -12.54,
        "pct_from_52w_low": 1.84
      }
    },
    "COLO-B.CO": {
      "price": 380.3,
      "pct_1d": 0.34,
      "pct_5d": 0.8,
      "pct_20d": -6.08,
      "pe_forward": 14.468867,
      "pe_trailing": 40.80472,
      "div_yield": 6.07,
      "volume_ratio": 0.12,
      "52w_high": 646.6,
      "52w_low": 369.7,
      "pct_from_52w_high": -41.18,
      "pct_from_52w_low": 2.87,
      "revenue_growth": 0.022,
      "earnings_growth": null,
      "market_cap": 85706989568,
      "sector": "Healthcare",
      "industry": "Medical Instruments & Supplies",
      "next_earnings_date": "2026-05-12",
      "technical": {
        "method": "yfinance_historical",
        "rsi": 46.2,
        "rsi_proxy": 46.2,
        "macd_line": -6.3803,
        "bb_upper": 393.5053,
        "bb_mid": 381.42,
        "bb_lower": 369.3347,
        "bb_position": 45.4,
        "atr": 7.7643,
        "stoch": 53.3,
        "stoch_proxy": 53.3,
        "sma50": 397.94,
        "sma200": 495.57,
        "sma50_vs_price": -4.43,
        "sma200_vs_price": -23.26,
        "volume_ratio": 0.12,
        "momentum_5d": 0.8,
        "momentum_20d": -6.08,
        "momentum_divergence": 6.88,
        "pct_from_52w_high": -41.18,
        "pct_from_52w_low": 2.87
      }
    },
    "GMAB.CO": {
      "price": 1696.0,
      "pct_1d": -0.59,
      "pct_5d": 4.24,
      "pct_20d": -1.62,
      "pe_forward": 16.03378,
      "pe_trailing": 19.647821,
      "div_yield": null,
      "volume_ratio": 0.06,
      "52w_high": 2257.0,
      "52w_low": 1275.0,
      "pct_from_52w_high": -24.86,
      "pct_from_52w_low": 33.02,
      "revenue_growth": 0.253,
      "earnings_growth": -0.728,
      "market_cap": 104123523072,
      "sector": "Healthcare",
      "industry": "Biotechnology",
      "next_earnings_date": "2026-08-06",
      "technical": {
        "method": "yfinance_historical",
        "rsi": 69.3,
        "rsi_proxy": 69.3,
        "macd_line": -0.4645,
        "bb_upper": 1735.0852,
        "bb_mid": 1628.85,
        "bb_lower": 1522.6148,
        "bb_position": 81.6,
        "atr": 42.2857,
        "stoch": 82.6,
        "stoch_proxy": 82.6,
        "sma50": 1689.28,
        "sma200": 1865.89,
        "sma50_vs_price": 0.4,
        "sma200_vs_price": -9.1,
        "volume_ratio": 0.06,
        "momentum_5d": 4.24,
        "momentum_20d": -1.62,
        "momentum_divergence": 5.86,
        "pct_from_52w_high": -24.86,
        "pct_from_52w_low": 33.02
      }
    },
    "GN.CO": {
      "price": 88.86,
      "pct_1d": -0.65,
      "pct_5d": 0.34,
      "pct_20d": -8.88,
      "pe_forward": 16.322767,
      "pe_trailing": 49.36667,
      "div_yield": null,
      "volume_ratio": 0.41,
      "52w_high": 125.9,
      "52w_low": 85.12,
      "pct_from_52w_high": -29.42,
      "pct_from_52w_low": 4.39,
      "revenue_growth": -0.082,
      "earnings_growth": null,
      "market_cap": 12939130880,
      "sector": "Healthcare",
      "industry": "Medical Devices",
      "next_earnings_date": "2026-05-06",
      "technical": {
        "method": "yfinance_historical",
        "rsi": 29.7,
        "rsi_proxy": 29.7,
        "macd_line": -1.9651,
        "bb_upper": 98.6849,
        "bb_mid": 92.297,
        "bb_lower": 85.9091,
        "bb_position": 23.1,
        "atr": 2.5071,
        "stoch": 18.5,
        "stoch_proxy": 18.5,
        "sma50": 96.02,
        "sma200": 103.33,
        "sma50_vs_price": -7.46,
        "sma200_vs_price": -14.01,
        "volume_ratio": 0.54,
        "momentum_5d": 0.34,
        "momentum_20d": -8.88,
        "momentum_divergence": 9.22,
        "pct_from_52w_high": -29.42,
        "pct_from_52w_low": 4.39
      }
    },
    "DEMANT.CO": {
      "price": 266.6,
      "pct_1d": 1.99,
      "pct_5d": 9.53,
      "pct_20d": 8.37,
      "pe_forward": 17.70277,
      "pe_trailing": 23.824844,
      "div_yield": null,
      "volume_ratio": 0.22,
      "52w_high": 284.4,
      "52w_low": 175.0,
      "pct_from_52w_high": -6.26,
      "pct_from_52w_low": 52.34,
      "revenue_growth": 0.034,
      "earnings_growth": -0.634,
      "market_cap": 56225570816,
      "sector": "Healthcare",
      "industry": "Medical Devices",
      "next_earnings_date": null,
      "technical": {
        "method": "yfinance_historical",
        "rsi": 68.2,
        "rsi_proxy": 68.2,
        "macd_line": 6.9059,
        "bb_upper": 262.3441,
        "bb_mid": 251.36,
        "bb_lower": 240.3759,
        "bb_position": 119.4,
        "atr": 6.7429,
        "stoch": 91.2,
        "stoch_proxy": 91.2,
        "sma50": 233.53,
        "sma200": 219.05,
        "sma50_vs_price": 14.16,
        "sma200_vs_price": 21.71,
        "volume_ratio": 0.25,
        "momentum_5d": 9.53,
        "momentum_20d": 8.37,
        "momentum_divergence": 1.16,
        "pct_from_52w_high": -6.26,
        "pct_from_52w_low": 52.34
      }
    },
    "RBREW.CO": {
      "price": 432.8,
      "pct_1d": 0.14,
      "pct_5d": 4.04,
      "pct_20d": 2.95,
      "pe_forward": 11.445466,
      "pe_trailing": 13.40353,
      "div_yield": 3.7,
      "volume_ratio": 0.12,
      "52w_high": 653.5,
      "52w_low": 394.6,
      "pct_from_52w_high": -33.77,
      "pct_from_52w_low": 9.68,
      "revenue_growth": 0.033,
      "earnings_growth": 0.4,
      "market_cap": 20736145408,
      "sector": "Consumer Defensive",
      "industry": "Beverages - Brewers",
      "next_earnings_date": "2026-04-21",
      "technical": {
        "method": "yfinance_historical",
        "rsi": 73.0,
        "rsi_proxy": 73.0,
        "macd_line": -0.5517,
        "bb_upper": 430.4167,
        "bb_mid": 416.45,
        "bb_lower": 402.4833,
        "bb_position": 108.5,
        "atr": 7.9714,
        "stoch": 95.1,
        "stoch_proxy": 95.1,
        "sma50": 426.95,
        "sma200": 501.95,
        "sma50_vs_price": 1.37,
        "sma200_vs_price": -13.78,
        "volume_ratio": 0.19,
        "momentum_5d": 4.04,
        "momentum_20d": 2.95,
        "momentum_divergence": 1.09,
        "pct_from_52w_high": -33.77,
        "pct_from_52w_low": 9.68
      }
    },
    "NDA-DK.CO": {
      "price": 121.1,
      "pct_1d": -0.08,
      "pct_5d": -1.5,
      "pct_20d": -2.02,
      "pe_forward": 11.966403,
      "pe_trailing": 11.907571,
      "div_yield": 5.92,
      "volume_ratio": 0.21,
      "52w_high": 127.75,
      "52w_low": 89.3,
      "pct_from_52w_high": -5.21,
      "pct_from_52w_low": 35.61,
      "revenue_growth": 0.014,
      "earnings_growth": -0.086,
      "market_cap": 410983563264,
      "sector": "Financial Services",
      "industry": "Banks - Regional",
      "next_earnings_date": "2026-07-16",
      "technical": {
        "method": "yfinance_historical",
        "rsi": 51.3,
        "rsi_proxy": 51.3,
        "macd_line": 0.8847,
        "bb_upper": 125.8346,
        "bb_mid": 121.8925,
        "bb_lower": 117.9504,
        "bb_position": 39.9,
        "atr": 2.0393,
        "stoch": 44.0,
        "stoch_proxy": 44.0,
        "sma50": 120.1,
        "sma200": 114.92,
        "sma50_vs_price": 0.84,
        "sma200_vs_price": 5.38,
        "volume_ratio": 0.25,
        "momentum_5d": -1.5,
        "momentum_20d": -2.02,
        "momentum_divergence": 0.52,
        "pct_from_52w_high": -5.21,
        "pct_from_52w_low": 35.61
      }
    },
    "DANSKE.CO": {
      "price": 344.9,
      "pct_1d": -0.4,
      "pct_5d": -0.66,
      "pct_20d": 3.02,
      "pe_forward": 10.817391,
      "pe_trailing": 12.309065,
      "div_yield": 4.89,
      "volume_ratio": 0.09,
      "52w_high": 355.7,
      "52w_low": 249.7,
      "pct_from_52w_high": -3.04,
      "pct_from_52w_low": 38.13,
      "revenue_growth": 0.009,
      "earnings_growth": 0.014,
      "market_cap": 278935404544,
      "sector": "Financial Services",
      "industry": "Banks - Regional",
      "next_earnings_date": "2026-07-17",
      "technical": {
        "method": "yfinance_historical",
        "rsi": 68.4,
        "rsi_proxy": 68.4,
        "macd_line": 6.3059,
        "bb_upper": 356.7925,
        "bb_mid": 338.845,
        "bb_lower": 320.8975,
        "bb_position": 66.9,
        "atr": 5.7714,
        "stoch": 65.8,
        "stoch_proxy": 65.8,
        "sma50": 329.98,
        "sma200": 289.64,
        "sma50_vs_price": 4.52,
        "sma200_vs_price": 19.08,
        "volume_ratio": 0.11,
        "momentum_5d": -0.66,
        "momentum_20d": 3.02,
        "momentum_divergence": -3.68,
        "pct_from_52w_high": -3.04,
        "pct_from_52w_low": 38.13
      }
    },
    "FLS.CO": {
      "price": 482.0,
      "pct_1d": -0.41,
      "pct_5d": -4.84,
      "pct_20d": -6.41,
      "pe_forward": 14.802348,
      "pe_trailing": 19.334135,
      "div_yield": 0.83,
      "volume_ratio": 0.31,
      "52w_high": 619.5,
      "52w_low": 363.0,
      "pct_from_52w_high": -22.2,
      "pct_from_52w_low": 32.78,
      "revenue_growth": -0.116,
      "earnings_growth": 1.951,
      "market_cap": 25985742848,
      "sector": "Industrials",
      "industry": "Specialty Industrial Machinery",
      "next_earnings_date": "2026-05-13",
      "technical": {
        "method": "yfinance_historical",
        "rsi": 32.6,
        "rsi_proxy": 32.6,
        "macd_line": -1.0834,
        "bb_upper": 530.9742,
        "bb_mid": 502.425,
        "bb_lower": 473.8757,
        "bb_position": 14.2,
        "atr": 16.5286,
        "stoch": 18.4,
        "stoch_proxy": 18.4,
        "sma50": 496.94,
        "sma200": 483.19,
        "sma50_vs_price": -3.01,
        "sma200_vs_price": -0.25,
        "volume_ratio": 0.32,
        "momentum_5d": -4.84,
        "momentum_20d": -6.41,
        "momentum_divergence": 1.57,
        "pct_from_52w_high": -22.2,
        "pct_from_52w_low": 32.78
      }
    },
    "VWS.CO": {
      "price": 172.15,
      "pct_1d": 0.76,
      "pct_5d": -0.84,
      "pct_20d": -2.85,
      "pe_forward": 15.974106,
      "pe_trailing": 27.067608,
      "div_yield": 0.43,
      "volume_ratio": 0.13,
      "52w_high": 203.0,
      "52w_low": 93.2,
      "pct_from_52w_high": -15.2,
      "pct_from_52w_low": 84.71,
      "revenue_growth": 0.144,
      "earnings_growth": 15.162,
      "market_cap": 168914206720,
      "sector": "Industrials",
      "industry": "Specialty Industrial Machinery",
      "next_earnings_date": "2026-05-06",
      "technical": {
        "method": "yfinance_historical",
        "rsi": 48.7,
        "rsi_proxy": 48.7,
        "macd_line": -2.8096,
        "bb_upper": 184.5533,
        "bb_mid": 174.215,
        "bb_lower": 163.8767,
        "bb_position": 40.0,
        "atr": 6.9857,
        "stoch": 41.1,
        "stoch_proxy": 41.1,
        "sma50": 185.76,
        "sma200": 162.01,
        "sma50_vs_price": -7.32,
        "sma200_vs_price": 6.26,
        "volume_ratio": 0.14,
        "momentum_5d": -0.84,
        "momentum_20d": -2.85,
        "momentum_divergence": 2.01,
        "pct_from_52w_high": -15.2,
        "pct_from_52w_low": 84.71
      }
    },
    "AMBU-B.CO": {
      "price": 60.3,
      "pct_1d": 2.38,
      "pct_5d": -2.9,
      "pct_20d": -9.73,
      "pe_forward": 19.60593,
      "pe_trailing": 33.687153,
      "div_yield": 0.7,
      "volume_ratio": 0.63,
      "52w_high": 111.8,
      "52w_low": 56.25,
      "pct_from_52w_high": -46.06,
      "pct_from_52w_low": 7.2,
      "revenue_growth": 0.012,
      "earnings_growth": -0.352,
      "market_cap": 15890753536,
      "sector": "Healthcare",
      "industry": "Medical Devices",
      "next_earnings_date": "2026-05-06",
      "technical": {
        "method": "yfinance_historical",
        "rsi": 27.2,
        "rsi_proxy": 27.2,
        "macd_line": -1.2299,
        "bb_upper": 67.3788,
        "bb_mid": 63.55,
        "bb_lower": 59.7212,
        "bb_position": 7.6,
        "atr": 1.9429,
        "stoch": 44.3,
        "stoch_proxy": 44.3,
        "sma50": 64.76,
        "sma200": 81.79,
        "sma50_vs_price": -6.89,
        "sma200_vs_price": -26.27,
        "volume_ratio": 0.64,
        "momentum_5d": -2.9,
        "momentum_20d": -9.73,
        "momentum_divergence": 6.83,
        "pct_from_52w_high": -46.06,
        "pct_from_52w_low": 7.2
      }
    },
    "NSIS-B.CO": {
      "price": 413.5,
      "pct_1d": -0.12,
      "pct_5d": 6.54,
      "pct_20d": 9.25,
      "pe_forward": 23.669256,
      "pe_trailing": 43.253136,
      "div_yield": 1.57,
      "volume_ratio": 0.11,
      "52w_high": 467.5,
      "52w_low": 336.8,
      "pct_from_52w_high": -11.55,
      "pct_from_52w_low": 22.77,
      "revenue_growth": 0.039,
      "earnings_growth": 0.075,
      "market_cap": 192785514496,
      "sector": "Basic Materials",
      "industry": "Specialty Chemicals",
      "next_earnings_date": null,
      "technical": {
        "method": "yfinance_historical",
        "rsi": 78.4,
        "rsi_proxy": 78.4,
        "macd_line": 6.7786,
        "bb_upper": 410.8134,
        "bb_mid": 384.31,
        "bb_lower": 357.8066,
        "bb_position": 105.1,
        "atr": 9.8571,
        "stoch": 96.4,
        "stoch_proxy": 96.4,
        "sma50": 383.06,
        "sma200": 390.36,
        "sma50_vs_price": 7.95,
        "sma200_vs_price": 5.93,
        "volume_ratio": 0.12,
        "momentum_5d": 6.54,
        "momentum_20d": 9.25,
        "momentum_divergence": -2.71,
        "pct_from_52w_high": -11.55,
        "pct_from_52w_low": 22.77
      }
    },
    "ROCK-B.CO": {
      "price": 222.0,
      "pct_1d": 0.82,
      "pct_5d": 0.91,
      "pct_20d": 12.18,
      "pe_forward": 14.910679,
      "pe_trailing": "Infinity",
      "div_yield": 1.88,
      "volume_ratio": 0.12,
      "52w_high": 299.7,
      "52w_low": 165.96,
      "pct_from_52w_high": -25.93,
      "pct_from_52w_low": 33.77,
      "revenue_growth": 0.0,
      "earnings_growth": null,
      "market_cap": 45894586368,
      "sector": "Industrials",
      "industry": "Building Products & Equipment",
      "next_earnings_date": "2026-08-19",
      "technical": {
        "method": "yfinance_historical",
        "rsi": 73.2,
        "rsi_proxy": 73.2,
        "macd_line": 7.3312,
        "bb_upper": 227.1708,
        "bb_mid": 207.88,
        "bb_lower": 188.5892,
        "bb_position": 86.6,
        "atr": 6.3786,
        "stoch": 94.4,
        "stoch_proxy": 94.4,
        "sma50": 196.74,
        "sma200": 207.84,
        "sma50_vs_price": 12.84,
        "sma200_vs_price": 6.81,
        "volume_ratio": 0.13,
        "momentum_5d": 0.91,
        "momentum_20d": 12.18,
        "momentum_divergence": -11.27,
        "pct_from_52w_high": -25.93,
        "pct_from_52w_low": 33.77
      }
    },
    "BAVA.CO": {
      "price": 177.5,
      "pct_1d": -0.28,
      "pct_5d": -1.06,
      "pct_20d": -7.36,
      "pe_forward": 16.633276,
      "pe_trailing": 11.762756,
      "div_yield": null,
      "volume_ratio": 0.53,
      "52w_high": 244.8,
      "52w_low": 165.8,
      "pct_from_52w_high": -27.49,
      "pct_from_52w_low": 7.06,
      "revenue_growth": -0.214,
      "earnings_growth": -0.926,
      "market_cap": 13519601664,
      "sector": "Healthcare",
      "industry": "Biotechnology",
      "next_earnings_date": "2026-05-13",
      "technical": {
        "method": "yfinance_historical",
        "rsi": 41.4,
        "rsi_proxy": 41.4,
        "macd_line": -3.3808,
        "bb_upper": 188.0482,
        "bb_mid": 180.76,
        "bb_lower": 173.4718,
        "bb_position": 27.6,
        "atr": 4.1643,
        "stoch": 43.4,
        "stoch_proxy": 43.4,
        "sma50": 187.85,
        "sma200": 200.38,
        "sma50_vs_price": -5.51,
        "sma200_vs_price": -11.42,
        "volume_ratio": 0.55,
        "momentum_5d": -1.06,
        "momentum_20d": -7.36,
        "momentum_divergence": 6.3,
        "pct_from_52w_high": -27.49,
        "pct_from_52w_low": 7.06
      }
    },
    "JYSK.CO": {
      "price": 937.0,
      "pct_1d": -0.05,
      "pct_5d": -1.37,
      "pct_20d": 2.35,
      "pe_forward": 10.07853,
      "pe_trailing": 11.281002,
      "div_yield": 2.67,
      "volume_ratio": 0.23,
      "52w_high": 981.0,
      "52w_low": 629.0,
      "pct_from_52w_high": -4.49,
      "pct_from_52w_low": 48.97,
      "revenue_growth": -0.081,
      "earnings_growth": -0.126,
      "market_cap": 53323493376,
      "sector": "Financial Services",
      "industry": "Banks - Regional",
      "next_earnings_date": "2026-05-06",
      "technical": {
        "method": "yfinance_historical",
        "rsi": 75.6,
        "rsi_proxy": 75.6,
        "macd_line": 12.7958,
        "bb_upper": 971.2921,
        "bb_mid": 921.775,
        "bb_lower": 872.2579,
        "bb_position": 65.4,
        "atr": 15.6071,
        "stoch": 68.9,
        "stoch_proxy": 68.9,
        "sma50": 908.93,
        "sma200": 832.22,
        "sma50_vs_price": 3.09,
        "sma200_vs_price": 12.59,
        "volume_ratio": 0.25,
        "momentum_5d": -1.37,
        "momentum_20d": 2.35,
        "momentum_divergence": -3.72,
        "pct_from_52w_high": -4.49,
        "pct_from_52w_low": 48.97
      }
    },
    "ISS.CO": {
      "price": 269.8,
      "pct_1d": 1.05,
      "pct_5d": 2.2,
      "pct_20d": 2.04,
      "pe_forward": 12.052617,
      "pe_trailing": 17.50811,
      "div_yield": 1.2,
      "volume_ratio": 0.22,
      "52w_high": 290.6,
      "52w_low": 172.9,
      "pct_from_52w_high": -7.16,
      "pct_from_52w_low": 56.04,
      "revenue_growth": -0.0,
      "earnings_growth": 0.001,
      "market_cap": 42299539456,
      "sector": "Industrials",
      "industry": "Specialty Business Services",
      "next_earnings_date": "2026-05-05",
      "technical": {
        "method": "yfinance_historical",
        "rsi": 83.7,
        "rsi_proxy": 83.7,
        "macd_line": 3.1721,
        "bb_upper": 270.676,
        "bb_mid": 261.77,
        "bb_lower": 252.864,
        "bb_position": 95.1,
        "atr": 4.1857,
        "stoch": 96.1,
        "stoch_proxy": 96.1,
        "sma50": 254.1,
        "sma200": 224.91,
        "sma50_vs_price": 6.18,
        "sma200_vs_price": 19.96,
        "volume_ratio": 0.27,
        "momentum_5d": 2.2,
        "momentum_20d": 2.04,
        "momentum_divergence": 0.16,
        "pct_from_52w_high": -7.16,
        "pct_from_52w_low": 56.04
      }
    },
    "ALSYDB.CO": {
      "price": 550.5,
      "pct_1d": -0.45,
      "pct_5d": -1.61,
      "pct_20d": 1.1,
      "pe_forward": 8.942859,
      "pe_trailing": 17.465101,
      "div_yield": 4.52,
      "volume_ratio": 0.13,
      "52w_high": 590.0,
      "52w_low": 436.0,
      "pct_from_52w_high": -6.69,
      "pct_from_52w_low": 26.26,
      "revenue_growth": 0.653,
      "earnings_growth": -0.268,
      "market_cap": 46781489152,
      "sector": "Financial Services",
      "industry": "Banks - Regional",
      "next_earnings_date": "2026-05-06",
      "technical": {
        "method": "yfinance_historical",
        "rsi": 72.6,
        "rsi_proxy": 72.6,
        "macd_line": 6.8791,
        "bb_upper": 582.2737,
        "bb_mid": 539.075,
        "bb_lower": 495.8763,
        "bb_position": 63.2,
        "atr": 10.0357,
        "stoch": 71.7,
        "stoch_proxy": 71.7,
        "sma50": 542.87,
        "sma200": 520.22,
        "sma50_vs_price": 1.41,
        "sma200_vs_price": 5.82,
        "volume_ratio": 0.1,
        "momentum_5d": -1.61,
        "momentum_20d": 1.1,
        "momentum_divergence": -2.71,
        "pct_from_52w_high": -6.69,
        "pct_from_52w_low": 26.26
      }
    },
    "NNIT.CO": {
      "price": 38.6,
      "pct_1d": 1.45,
      "pct_5d": -1.78,
      "pct_20d": -4.46,
      "pe_forward": 9.331177,
      "pe_trailing": null,
      "div_yield": null,
      "volume_ratio": 0.29,
      "52w_high": 70.5,
      "52w_low": 36.5,
      "pct_from_52w_high": -45.25,
      "pct_from_52w_low": 5.75,
      "revenue_growth": -0.057,
      "earnings_growth": null,
      "market_cap": 961285888,
      "sector": "Technology",
      "industry": "Information Technology Services",
      "next_earnings_date": "2026-05-12",
      "technical": {
        "method": "yfinance_historical",
        "rsi": 40.7,
        "rsi_proxy": 40.7,
        "macd_line": -0.8012,
        "bb_upper": 41.6429,
        "bb_mid": 39.9275,
        "bb_lower": 38.2121,
        "bb_position": 11.3,
        "atr": 1.1893,
        "stoch": 41.6,
        "stoch_proxy": 41.6,
        "sma50": 41.8,
        "sma200": 48.17,
        "sma50_vs_price": -7.65,
        "sma200_vs_price": -19.87,
        "volume_ratio": 0.15,
        "momentum_5d": -1.78,
        "momentum_20d": -4.46,
        "momentum_divergence": 2.68,
        "pct_from_52w_high": -45.25,
        "pct_from_52w_low": 5.75
      }
    }
  }
}