{
  "symbol": "COLOb:xcse",
  "name": "Coloplast B",
  "overview": "",
  "financials": {},
  "news": [
    {
      "date": "2026-06-19",
      "title": "Gieves & Hawkes’s Savile Row home sold to Danish catheter tycoon",
      "source": "The Telegraph",
      "summary": "The Savile Row home of luxury menswear tailor Gieves & Hawkes has been snapped up for £31m by a Danish catheter billionaire.",
      "url": "https://www.telegraph.co.uk/business/2026/06/19/gieves-hawkes-savile-row-home-sold-to-catheter-tycoon/"
    },
    {
      "date": "2026-06-03",
      "title": "Coloplast's Next Generation Inflatable Penile Prosthesis Approved by the FDA - can help millions of men",
      "source": "Nasdaq Copenhagen",
      "summary": "Investor Nyheder",
      "url": "https://view.news.eu.nasdaq.com/view?id=b93893d6bf32f3ff53084070841da580e&lang=en&src=listed"
    }
  ],
  "last_updated": "2026-07-24T16:57:13.535200+00:00"
}